<window id="132">
    <defaultcontrol>3</defaultcontrol>
    <include>Fade_In_WindowOpen</include>
    <include>Fade_Out_WindowClose</include>
    <coordinates>
        <system>1</system>
        <left>0</left>
        <top>0</top>
    </coordinates>
    <controls>
        <control type="image">
            <left>0</left>
            <top>0</top>
            <width>1920</width>
            <height>1080</height>
            <texture>filter_keyboard_shadow.png</texture>
        </control>
        <control type="group">
            <include>Zoom_In_WindowOpen</include>
            <include>Zoom_Out_WindowClose</include>
            <control type="image">
                <description>background image</description>
                <left>96</left>
                <top>68</top>
                <width>1726</width>
                <height>946</height>
                <texture>dialogs\dialog-background-tall.png</texture>
            </control>
            <control type="group">
                <left>188</left>
                <top>141</top>
                <width>1545</width>
                <height>720</height>
                <control type="image">
                    <description>dialog icon</description>
                    <left>710</left>
                    <top>34</top>
                    <width>126</width>
                    <height>63</height>
                    <texture>dialogs\setcontent-dialog-icon.png</texture>
                </control>
                <control type="label" id="1">
                    <description>heading label</description>
                    <left>0</left>
                    <top>102</top>
                    <width>1545</width>
                    <align>center</align>
                    <font>Heading</font>
                    <label>20333</label>
                    <textcolor>Text</textcolor>
                </control>
                <control type="spincontrolex" id="3">
                    <description>Content Picker</description>
                    <left>45</left>
                    <top>180</top>
                    <width>1455</width>
                    <height>69</height>
                    <font>Default</font>
                    <texturefocus border="4,5,6,8">controls\button_f.png</texturefocus>
                    <texturenofocus border="4,5,6,8">controls\button_nf.png</texturenofocus>
                    <textureup>controls\sortup_nf.png</textureup>
                    <texturedown>controls\sortdown_nf.png</texturedown>
                    <textureupfocus>controls\sortup_f.png</textureupfocus>
                    <texturedownfocus>controls\sortdown_f.png</texturedownfocus>
                    <textcolor>Text</textcolor>
                    <disabledcolor>DisabledText</disabledcolor>
                    <textoffsetx>22</textoffsetx>
                    <aligny>center</aligny>
                    <reverse>yes</reverse>
                    <label>20344</label>
                    <onup>29</onup>
                    <ondown>4</ondown>
                    <onleft>3</onleft>
                    <onright>3</onright>
                </control>
                <control type="list" id="4">
                    <left>45</left>
                    <top>264</top>
                    <width>720</width>
                    <height>276</height>
                    <onleft>5</onleft>
                    <onright>5</onright>
                    <onup>3</onup>
                    <ondown>6</ondown>
                    <pagecontrol>-</pagecontrol>
                    <scrolltime>200</scrolltime>
                    <itemlayout height="69">
                        <control type="image">
                            <left>0</left>
                            <top>0</top>
                            <width>720</width>
                            <height>69</height>
                            <texture border="8">controls\button_nf.png</texture>
                        </control>
                        <control type="image">
                            <left>15</left>
                            <top>6</top>
                            <width>52</width>
                            <height>52</height>
                            <info>ListItem.Icon</info>
                        </control>
                        <control type="label">
                            <left>82</left>
                            <top>6</top>
                            <width>622</width>
                            <height>52</height>
                            <font>Medium_Large</font>
                            <aligny>center</aligny>
                            <selectedcolor>Highlight</selectedcolor>
                            <textcolor>Text</textcolor>
                            <align>left</align>
                            <info>ListItem.Label</info>
                        </control>
                    </itemlayout>
                    <focusedlayout height="69">
                        <control type="image">
                            <left>0</left>
                            <top>0</top>
                            <width>720</width>
                            <height>69</height>
                            <visible>!Control.HasFocus(4)</visible>
                            <texture border="4,5,6,8">controls\button_nf.png</texture>
                        </control>
                        <control type="image">
                            <left>0</left>
                            <top>0</top>
                            <width>720</width>
                            <height>69</height>
                            <visible>Control.HasFocus(4)</visible>
                            <texture border="4,5,6,8">controls\button_f.png</texture>
                        </control>
                        <control type="image">
                            <left>15</left>
                            <top>6</top>
                            <width>52</width>
                            <height>52</height>
                            <info>ListItem.Icon</info>
                        </control>
                        <control type="label">
                            <left>82</left>
                            <top>6</top>
                            <width>622</width>
                            <height>52</height>
                            <font>Medium_Large</font>
                            <aligny>center</aligny>
                            <selectedcolor>Highlight</selectedcolor>
                            <textcolor>Text</textcolor>
                            <align>left</align>
                            <info>ListItem.Label</info>
                        </control>
                    </focusedlayout>
                </control>
                <control type="grouplist" id="5">
                    <description>control area</description>
                    <left>780</left>
                    <top>264</top>
                    <width>720</width>
                    <height>276</height>
                    <itemgap>0</itemgap>
                    <onup>3</onup>
                    <ondown>6</ondown>
                    <onleft>4</onleft>
                    <onright>4</onright>
                </control>
                <control type="image">
                    <description>scraper image</description>
                    <left>45</left>
                    <top>586</top>
                    <width>720</width>
                    <height>128</height>
                    <aspectratio>keep</aspectratio>
                    <info>ListItem.Icon</info>
                </control>
                <control type="button" id="6">
                    <description>Set Content Button</description>
                    <left>960</left>
                    <top>550</top>
                    <width>375</width>
                    <height>69</height>
                    <align>center</align>
                    <texturenofocus border="8">controls\button_nf.png</texturenofocus>
                    <texturefocus border="8">controls\button_f.png</texturefocus>
                    <textcolor>Text</textcolor>
                    <disabledcolor>DisabledText</disabledcolor>
                    <label>5</label>
                    <font>Default</font>
                    <onleft>6</onleft>
                    <onright>6</onright>
                    <onup>5</onup>
                    <ondown>28</ondown>
                </control>
                <control type="button" id="28">
                    <description>OK button</description>
                    <left>960</left>
                    <top>620</top>
                    <width>375</width>
                    <height>69</height>
                    <align>center</align>
                    <texturenofocus border="8">controls\button_green_nf.png</texturenofocus>
                    <texturefocus border="8">controls\button_green_f.png</texturefocus>
                    <textcolor>Text</textcolor>
                    <disabledcolor>DisabledText</disabledcolor>
                    <label>186</label>
                    <font>Default</font>
                    <onleft>28</onleft>
                    <onright>28</onright>
                    <onup>6</onup>
                    <ondown>29</ondown>
                </control>
                <control type="button" id="29">
                    <description>Cancel button</description>
                    <left>960</left>
                    <top>690</top>
                    <width>375</width>
                    <height>69</height>
                    <align>center</align>
                    <texturenofocus border="8">controls\button_red_nf.png</texturenofocus>
                    <texturefocus border="8">controls\button_red_f.png</texturefocus>
                    <textcolor>Text</textcolor>
                    <disabledcolor>DisabledText</disabledcolor>
                    <label>222</label>
                    <font>Default</font>
                    <onleft>29</onleft>
                    <onright>29</onright>
                    <onup>28</onup>
                    <ondown>3</ondown>
                </control>
            </control>
        </control>
        <control type="button" id="7">
            <description>Default Button</description>
            <left>0</left>
            <top>0</top>
            <height>69</height>
            <font>Medium_Large</font>
            <textcolor>Text</textcolor>
            <textoffsetx>22</textoffsetx>
            <texturefocus border="4,5,6,8">controls\button_f.png</texturefocus>
            <texturenofocus border="4,5,6,8">controls\button_nf.png</texturenofocus>
        </control>
        <control type="radiobutton" id="8">
            <description>Default RadioButton</description>
            <left>0</left>
            <top>0</top>
            <height>69</height>
            <textoffsetx>22</textoffsetx>
            <font>Medium_Large</font>
            <texturefocus border="4,5,6,8">controls\button_f.png</texturefocus>
            <texturenofocus border="4,5,6,8">controls\button_nf.png</texturenofocus>
            <textureradiofocus>controls\radiobutton_f.png</textureradiofocus>
            <textureradionofocus>controls\radiobutton_nf.png</textureradionofocus>
            <pulseonselect>no</pulseonselect>
        </control>
        <include>Debug</include>
    </controls>
</window>